moretype/__init__.py
moretype/exceptions.py
moretype/moretype.pyi
moretype/test.py
moretype-1.6.1.dist-info/LICENCE.txt
moretype-1.6.1.dist-info/METADATA
moretype-1.6.1.dist-info/WHEEL
moretype-1.6.1.dist-info/top_level.txt
moretype-1.6.1.dist-info/RECORD
